{
  "作者": "菜妮丝https://cainisi.cf",
  "站名": "大米星球",
  "主页url": "https://dami2.me",
  
  "分类": "Netflix$/label/netflix#电影$/vodtype/20#电视剧$/vodtype/21#动漫$/vodtype/22#综艺$/vodtype/23",
  
  "分类url": "https://dami2.me{cateId}/page/{catePg}.html",
  
  "副标题": "module-item-note\">&&</div>",
  
  "搜索模式": "0",
  "搜索后缀": "/voddetail/",
  
  "导演": "导演：&&</div>",
  "主演": "主演：&&</div>",
  "简介": "<p>&&</p>",
  
  "线路数组": "data-dropdown-value=&&</div>",
  "线路标题": "<span>&&</small>[替换:</span><small>>>👉]+集♥",
  
  "播放数组": "module-play-list-base\">&&</div>"
}